{"testi/ortega-y-gasset/conversación_en_el_golf_o_la_idea_del_dharma#002":{"a":[{"href":"testi/hegel/the_philosophy_of_fine_art","title":"The Philosophy of Fine Art","philosopher":"Hegel","shared":1},{"href":"testi/kant/critique_of_judgement","title":"CRITIQUE OF JUDGEMENT","philosopher":"Kant","shared":1},{"href":"testi/ortega-y-gasset/el_alpe_y_la_sierra","title":"El alpe y la sierra","philosopher":"Ortega y Gasset","shared":1},{"href":"testi/hobbes/elements_of_law_natural_and_politic","title":"Elements of Law, Natural and Politic","philosopher":"Hobbes","shared":2},{"href":"testi/hobbes/leviathan","title":"Leviathan","philosopher":"Hobbes","shared":2},{"href":"testi/hume/a_treatise_of_human_nature","title":"A TREATISE OF HUMAN NATURE","philosopher":"Hume","shared":1}],"c":[{"href":"testi/descartes/les_principes_de_la_philosophie","title":"LES PRINCIPES DE LA PHILOSOPHIE","philosopher":"Descartes","pair":["empiricism","innatism"]},{"href":"testi/descartes/lettres","title":"LETTRES","philosopher":"Descartes","pair":["empiricism","innatism"]},{"href":"testi/descartes/méditations_métaphysiques","title":"MÉDITATIONS MÉTAPHYSIQUES","philosopher":"Descartes","pair":["empiricism","innatism"]},{"href":"testi/plato/meno","title":"MENO","philosopher":"Plato","pair":["empiricism","innatism"]},{"href":"testi/plato/phaedo","title":"PHAEDO","philosopher":"Plato","pair":["empiricism","innatism"]},{"href":"testi/plato/phaedrus","title":"PHAEDRUS","philosopher":"Plato","pair":["empiricism","innatism"]}]}}